dynamodump/__init__.py
dynamodump/dynamodump.py
dynamodump-1.11.1.dist-info/licenses/LICENSE
dynamodump-1.11.1.dist-info/METADATA
dynamodump-1.11.1.dist-info/WHEEL
dynamodump-1.11.1.dist-info/entry_points.txt
dynamodump-1.11.1.dist-info/top_level.txt
dynamodump-1.11.1.dist-info/RECORD
