Metadata-Version: 2.4
Name: dynamodump
Version: 1.11.1
Summary: Simple backup and restore for Amazon DynamoDB using AWS SDK for Python (boto3)
Home-page: https://github.com/bchew/dynamodump
Author: Benny Chew
Author-email: noreply@bennychew.com
Project-URL: Releases, https://github.com/bchew/dynamodump/releases
Classifier: Programming Language :: Python :: 3
Classifier: License :: OSI Approved :: MIT License
Requires-Python: >=3.10
License-File: LICENSE
Requires-Dist: boto3==1.40.43
Requires-Dist: six==1.17.0
Dynamic: author
Dynamic: author-email
Dynamic: classifier
Dynamic: description
Dynamic: description-content-type
Dynamic: home-page
Dynamic: license-file
Dynamic: project-url
Dynamic: requires-dist
Dynamic: requires-python
Dynamic: summary
